habits_to_streaks/__init__.py
habits_to_streaks/cli.py
habits_to_streaks/converter.py
habits_to_streaks/models.py
habits_to_streaks-1.0.0.dist-info/METADATA
habits_to_streaks-1.0.0.dist-info/WHEEL
habits_to_streaks-1.0.0.dist-info/entry_points.txt
habits_to_streaks-1.0.0.dist-info/licenses/LICENSE
habits_to_streaks-1.0.0.dist-info/RECORD
